systemd_gpio.py
systemd_gpio-0.1.0.dist-info/LICENSE.txt
systemd_gpio-0.1.0.dist-info/METADATA
systemd_gpio-0.1.0.dist-info/WHEEL
systemd_gpio-0.1.0.dist-info/entry_points.txt
systemd_gpio-0.1.0.dist-info/top_level.txt
systemd_gpio-0.1.0.dist-info/RECORD
