Metadata-Version: 2.1
Name: systemd-gpio
Version: 0.1.0
Summary: Use systemd to configure commands to run when a GPIO button is pressed on a Raspberry Pi
Author-email: Leo Singer <leo.p.singer@nasa.gov>
License: Apache-2.0
Classifier: Development Status :: 3 - Alpha
Classifier: Operating System :: POSIX :: Linux
Classifier: Topic :: Home Automation
Classifier: Topic :: Scientific/Engineering
Classifier: Topic :: Software Development :: Embedded Systems
Classifier: Topic :: System :: Boot :: Init
Requires-Python: >=3.8
License-File: LICENSE.txt
Requires-Dist: click
Requires-Dist: gpiozero
